pymysqlpool/__init__.py
pymysqlpool/pool.py
test/__init__.py
test/test_pool.py
pymysql_pooling-1.0.6.dist-info/LICENSE
pymysql_pooling-1.0.6.dist-info/METADATA
pymysql_pooling-1.0.6.dist-info/WHEEL
pymysql_pooling-1.0.6.dist-info/top_level.txt
pymysql_pooling-1.0.6.dist-info/RECORD
