Metadata-Version: 2.1
Name: pymysql-pooling
Version: 1.0.6
Summary: pymysql-based database connection pool
Home-page: https://github.com/prprprus/PyMySQLPool
License: UNKNOWN
Platform: UNKNOWN
Classifier: Programming Language :: Python :: 3
Classifier: License :: OSI Approved :: MIT License
Classifier: Operating System :: OS Independent
